spikecomparison/__init__.py
spikecomparison/basecomparison.py
spikecomparison/collisioncomparison.py
spikecomparison/comparisontools.py
spikecomparison/groundtruthcomparison.py
spikecomparison/groundtruthstudy.py
spikecomparison/multisortingcomparison.py
spikecomparison/studytools.py
spikecomparison/symmetricsortingcomparison.py
spikecomparison/version.py
spikecomparison-0.3.3.dist-info/LICENSE
spikecomparison-0.3.3.dist-info/METADATA
spikecomparison-0.3.3.dist-info/WHEEL
spikecomparison-0.3.3.dist-info/top_level.txt
spikecomparison-0.3.3.dist-info/RECORD
