Metadata-Version: 2.1
Name: spikecomparison
Version: 0.3.3
Summary: Python toolkit for analysis, visualization, and comparison of spike sorting output
Home-page: https://github.com/alejoe91/spikecomparison
Author: Alessio Buccino, Cole Hurwitz, Samuel Garcia, Jeremy Magland, Matthias Hennig
Author-email: alessiop.buccino@gmail.com
License: UNKNOWN
Platform: UNKNOWN
Classifier: Programming Language :: Python :: 3
Classifier: License :: OSI Approved :: Apache Software License
Classifier: Operating System :: OS Independent
Requires-Dist: numpy
Requires-Dist: scipy
Requires-Dist: pandas
Requires-Dist: networkx
Requires-Dist: joblib
Requires-Dist: spikeextractors (>=0.9.7)
Requires-Dist: spiketoolkit (>=0.7.6)
Requires-Dist: spikesorters (>=0.4.5)
